levrt/utils.cpython-310-x86_64-linux-gnu.so
levrt/__init__.pyi
levrt/core.cpython-310-x86_64-linux-gnu.so
levrt/__init__.py
levrt/progress.cpython-310-x86_64-linux-gnu.so
levrt/__main__.py
levrt/annot/cats.py
levrt/annot/core.cpython-310-x86_64-linux-gnu.so
levrt/annot/__init__.py
levrt-1.3.12.dist-info/METADATA
levrt-1.3.12.dist-info/top_level.txt
levrt-1.3.12.dist-info/WHEEL
levrt-1.3.12.dist-info/RECORD
