Metadata-Version: 2.1
Name: levrt
Version: 1.3.12
Summary: UNKNOWN
Home-page: UNKNOWN
License: UNKNOWN
Platform: UNKNOWN
Requires-Dist: msgpack (~=1.0)
Requires-Dist: motor (~=2.5)
Requires-Dist: nats-py (>=2.0.0)
Requires-Dist: sympy (>=1.9)
Requires-Dist: httpx (>=0.22.0)
Requires-Dist: aiofiles (>=0.8.0)
